[
  {
    "id": "432d9ed1-e330-4953-ac33-f51a60a5799b",
    "model": "Camry",
    "image": "./images/car23.min.jpg",
    "rentPerDay": 200000,
    "capacity": 6,
    "description": " Intermittent rear wiper w/washer. Energy absorbing front/rear bumpers. Engine mounts -inc: (2) solid, (1) liquid-filled."
  },
  {
    "id": "32e7e56f-1a00-455f-bf4b-dbd2c8c4daaf",
    "model": "Pathfiner",
    "image": "./images/car24.min.jpg",
    "rentPerDay": 600000,
    "capacity": 6,
    "description": " 200mm front axle. Roof mounted antenna. Cargo compartment cover. Rear bench seat -inc: (3) adjustable headrests.",
    "availableAt": "2022-03-23T15:49:05.563Z"
  },
  {
    "id": "645628b0-66be-4489-90e5-3097656c8979",
    "model": "Aston Martin",
    "image": "../images/car003.jpg",
    "capacity": 2,
    "rentPerDay": 9000000,
    "availableAt": "2022-03-23T15:49:05.563Z",
    "description": "this is exotic car from England"
  }
]
 